combop/__init__.py
combop-0.0.0.dist-info/LICENSE
combop-0.0.0.dist-info/WHEEL
combop-0.0.0.dist-info/METADATA
combop-0.0.0.dist-info/RECORD
