Metadata-Version: 2.1
Name: combop
Version: 0.0.0
Summary: Combop - A combinatorial optimization library
License: CC0-1.0
Author: Rafał Majewski
Author-email: goodheropl@gmail.com
Requires-Python: >=3.10,<4.0
Classifier: License :: CC0 1.0 Universal (CC0 1.0) Public Domain Dedication
Classifier: Programming Language :: Python :: 3
Classifier: Programming Language :: Python :: 3.10
